setup.py
zhr_demo/__init__.py
zhr_demo.egg-info/PKG-INFO
zhr_demo.egg-info/SOURCES.txt
zhr_demo.egg-info/dependency_links.txt
zhr_demo.egg-info/top_level.txt