Metadata-Version: 2.1
Name: zhr-demo
Version: 0.1.0
Summary: demo
Home-page: UNKNOWN
Author: zaoheren
Author-email: zaoheren@hotmail.com
License: UNKNOWN
Platform: UNKNOWN
Requires-Python: >=3.6
